 [
  { "value" : "aa", "name" : "Afar" },
  { "value" : "ab", "name" : "Abkhazian" },
  { "value" : "af", "name" : "Afrikaans" },
  { "value" : "ak", "name" : "Akan" },
  { "value" : "sq", "name" : "Albanian" },
  { "value" : "am", "name" : "Amharic" },
  { "value" : "ar", "name" : "Arabic" },
  { "value" : "an", "name" : "Aragonese" },
  { "value" : "hy", "name" : "Armenian" },
  { "value" : "as", "name" : "Assamese" },
  { "value" : "av", "name" : "Avaric" },
  { "value" : "ae", "name" : "Avestan" },
  { "value" : "ay", "name" : "Aymara" },
  { "value" : "az", "name" : "Azerbaijani" },
  { "value" : "ba", "name" : "Bashkir" },
  { "value" : "bm", "name" : "Bambara" },
  { "value" : "eu", "name" : "Basque" },
  { "value" : "be", "name" : "Belarusian" },
  { "value" : "bn", "name" : "Bengali" },
  { "value" : "bh", "name" : "Bihari languages" },
  { "value" : "bi", "name" : "Bislama" },
  { "value" : "bs", "name" : "Bosnian" },
  { "value" : "br", "name" : "Breton" },
  { "value" : "bg", "name" : "Bulgarian" },
  { "value" : "my", "name" : "Burmese" },
  { "value" : "ca", "name" : "Catalan" },
  { "value" : "ch", "name" : "Chamorro" },
  { "value" : "ce", "name" : "Chechen" },
  { "value" : "zh", "name" : "Chino" },
  { "value" : "zh_HANS", "name" : "Simplified Chinese" },
  { "value" : "zh_HANT", "name" : "Traditional Chinese" },
  { "value" : "cu", "name" : "Church Slavic" },
  { "value" : "cv", "name" : "Chuvash" },
  { "value" : "kw", "name" : "Cornish" },
  { "value" : "co", "name" : "Corsican" },
  { "value" : "cr", "name" : "Cree" },
  { "value" : "cs", "name" : "Czech" },
  { "value" : "da", "name" : "Danish" },
  { "value" : "dv", "name" : "Divehi" },
  { "value" : "nl", "name" : "Dutch" },
  { "value" : "dz", "name" : "Dzongkha" },
  { "value" : "en", "name" : "Inglés" },
  { "value" : "eo", "name" : "Esperanto" },
  { "value" : "et", "name" : "Estonian" },
  { "value" : "ee", "name" : "Ewe" },
  { "value" : "fo", "name" : "Faroese" },
  { "value" : "fj", "name" : "Fijian" },
  { "value" : "fi", "name" : "Finnish" },
  { "value" : "fr", "name" : "Francés" },
  { "value" : "fy", "name" : "Western Frisian" },
  { "value" : "ff", "name" : "Fulah" },
  { "value" : "ka", "name" : "Georgian" },
  { "value" : "de", "name" : "Alemán" },
  { "value" : "gd", "name" : "Gaelic" },
  { "value" : "ga", "name" : "Irish" },
  { "value" : "gl", "name" : "Galician" },
  { "value" : "gv", "name" : "Manx" },
  { "value" : "el", "name" : "Greek" },
  { "value" : "gn", "name" : "Guarani" },
  { "value" : "gu", "name" : "Gujarati" },
  { "value" : "ht", "name" : "Haitian" },
  { "value" : "ha", "name" : "Hausa" },
  { "value" : "he", "name" : "Hebreo" },
  { "value" : "hz", "name" : "Herero" },
  { "value" : "hi", "name" : "Hindi" },
  { "value" : "ho", "name" : "Hiri Motu" },
  { "value" : "hr", "name" : "Croatian" },
  { "value" : "hu", "name" : "Hungarian" },
  { "value" : "ig", "name" : "Igbo" },
  { "value" : "is", "name" : "Icelandic" },
  { "value" : "io", "name" : "Ido" },
  { "value" : "ii", "name" : "Sichuan Yi" },
  { "value" : "iu", "name" : "Inuktitut" },
  { "value" : "ie", "name" : "Interlingue" },
  { "value" : "ia", "name" : "Interlingua" },
  { "value" : "id", "name" : "Indonesian" },
  { "value" : "ik", "name" : "Inupiaq" },
  { "value" : "it", "name" : "Italiano" },
  { "value" : "jv", "name" : "Javanese" },
  { "value" : "ja", "name" : "Japonés" },
  { "value" : "kl", "name" : "Kalaallisut" },
  { "value" : "kn", "name" : "Kannada" },
  { "value" : "ks", "name" : "Kashmiri" },
  { "value" : "kr", "name" : "Kanuri" },
  { "value" : "kk", "name" : "Kazakh" },
  { "value" : "km", "name" : "Central Khmer" },
  { "value" : "ki", "name" : "Kikuyu" },
  { "value" : "rw", "name" : "Kinyarwanda" },
  { "value" : "ky", "name" : "Kirghiz" },
  { "value" : "kv", "name" : "Komi" },
  { "value" : "kg", "name" : "Kongo" },
  { "value" : "ko", "name" : "Koreano" },
  { "value" : "kj", "name" : "Kuanyama" },
  { "value" : "ku", "name" : "Kurdish" },
  { "value" : "lo", "name" : "Lao" },
  { "value" : "la", "name" : "Latín" },
  { "value" : "lv", "name" : "Latvian" },
  { "value" : "li", "name" : "Limburgan" },
  { "value" : "ln", "name" : "Lingala" },
  { "value" : "lt", "name" : "Lithuanian" },
  { "value" : "lb", "name" : "Luxembourgish" },
  { "value" : "lu", "name" : "Luba-Katanga" },
  { "value" : "lg", "name" : "Ganda" },
  { "value" : "mk", "name" : "Macedonian" },
  { "value" : "mh", "name" : "Marshallese" },
  { "value" : "ml", "name" : "Malayalam" },
  { "value" : "mi", "name" : "Maori" },
  { "value" : "mr", "name" : "Marathi" },
  { "value" : "ms", "name" : "Malay" },
  { "value" : "mg", "name" : "Malagasy" },
  { "value" : "mt", "name" : "Maltese" },
  { "value" : "mn", "name" : "Mongolian" },
  { "value" : "na", "name" : "Nauru" },
  { "value" : "nv", "name" : "Navajo" },
  { "value" : "nr", "name" : "Ndebele, South" },
  { "value" : "nd", "name" : "Ndebele, North" },
  { "value" : "ng", "name" : "Ndonga" },
  { "value" : "ne", "name" : "Nepali" },
  { "value" : "nn", "name" : "Norwegian Nynorsk" },
  { "value" : "nb", "name" : "Bokmål, Norwegian" },
  { "value" : "no", "name" : "Norwegian" },
  { "value" : "ny", "name" : "Chichewa" },
  { "value" : "oc", "name" : "Occitan" },
  { "value" : "oj", "name" : "Ojibwa" },
  { "value" : "or", "name" : "Oriya" },
  { "value" : "om", "name" : "Oromo" },
  { "value" : "os", "name" : "Ossetian" },
  { "value" : "pa", "name" : "Panjabi" },
  { "value" : "fa", "name" : "Persian" },
  { "value" : "pi", "name" : "Pali" },
  { "value" : "pl", "name" : "Polish" },
  { "value" : "pt", "name" : "Portugués" },
  { "value" : "ps", "name" : "Pushto" },
  { "value" : "qu", "name" : "Quechua" },
  { "value" : "rm", "name" : "Romansh" },
  { "value" : "ro", "name" : "Romanian" },
  { "value" : "rn", "name" : "Rundi" },
  { "value" : "ru", "name" : "Ruso" },
  { "value" : "sg", "name" : "Sango" },
  { "value" : "sa", "name" : "Sanskrit" },
  { "value" : "si", "name" : "Sinhala" },
  { "value" : "sk", "name" : "Slovak" },
  { "value" : "sl", "name" : "Slovenian" },
  { "value" : "se", "name" : "Northern Sami" },
  { "value" : "sm", "name" : "Samoan" },
  { "value" : "sn", "name" : "Shona" },
  { "value" : "sd", "name" : "Sindhi" },
  { "value" : "so", "name" : "Somali" },
  { "value" : "st", "name" : "Sotho, Southern" },
  { "value" : "es", "name" : "Español" },
  { "value" : "sc", "name" : "Sardinian" },
  { "value" : "sr", "name" : "Serbian" },
  { "value" : "ss", "name" : "Swati" },
  { "value" : "su", "name" : "Sundanese" },
  { "value" : "sw", "name" : "Swahili" },
  { "value" : "sv", "name" : "Swedish" },
  { "value" : "ty", "name" : "Tahitian" },
  { "value" : "ta", "name" : "Tamil" },
  { "value" : "tt", "name" : "Tatar" },
  { "value" : "te", "name" : "Telugu" },
  { "value" : "tg", "name" : "Tajik" },
  { "value" : "tl", "name" : "Tagalog" },
  { "value" : "th", "name" : "Thai" },
  { "value" : "bo", "name" : "Tibetan" },
  { "value" : "ti", "name" : "Tigrinya" },
  { "value" : "to", "name" : "Tonga (Tonga Islands)" },
  { "value" : "tn", "name" : "Tswana" },
  { "value" : "ts", "name" : "Tsonga" },
  { "value" : "tk", "name" : "Turkmen" },
  { "value" : "tr", "name" : "Turkish" },
  { "value" : "tw", "name" : "Twi" },
  { "value" : "ug", "name" : "Uighur" },
  { "value" : "uk", "name" : "Ukrainian" },
  { "value" : "ur", "name" : "Urdu" },
  { "value" : "uz", "name" : "Uzbek" },
  { "value" : "ve", "name" : "Venda" },
  { "value" : "vi", "name" : "Vietnamese" },
  { "value" : "vo", "name" : "Volapük" },
  { "value" : "cy", "name" : "Welsh" },
  { "value" : "wa", "name" : "Walloon" },
  { "value" : "wo", "name" : "Wolof" },
  { "value" : "xh", "name" : "Xhosa" },
  { "value" : "yi", "name" : "Yiddish" },
  { "value" : "yo", "name" : "Yoruba" },
  { "value" : "za", "name" : "Zhuang" },
  { "value" : "zu", "name" : "Zulu"}
  ]
